pydantic_core-2.41.3.dist-info/METADATA
pydantic_core-2.41.3.dist-info/WHEEL
pydantic_core-2.41.3.dist-info/licenses/LICENSE
pydantic_core/__init__.py
pydantic_core/_pydantic_core.cpython-310-darwin.so
pydantic_core/_pydantic_core.pyi
pydantic_core/core_schema.py
pydantic_core/py.typed
pydantic_core-2.41.3.dist-info/RECORD
