Metadata-Version: 2.4
Name: pydantic_core
Version: 2.41.3
Classifier: Development Status :: 3 - Alpha
Classifier: Programming Language :: Python
Classifier: Programming Language :: Python :: 3
Classifier: Programming Language :: Python :: 3 :: Only
Classifier: Programming Language :: Python :: 3.9
Classifier: Programming Language :: Python :: 3.10
Classifier: Programming Language :: Python :: 3.11
Classifier: Programming Language :: Python :: 3.12
Classifier: Programming Language :: Python :: 3.13
Classifier: Programming Language :: Python :: 3.14
Classifier: Programming Language :: Python :: Implementation :: CPython
Classifier: Programming Language :: Python :: Implementation :: PyPy
Classifier: Programming Language :: Python :: Implementation :: GraalPy
Classifier: Programming Language :: Rust
Classifier: Framework :: Pydantic
Classifier: Intended Audience :: Developers
Classifier: Intended Audience :: Information Technology
Classifier: Operating System :: POSIX :: Linux
Classifier: Operating System :: Microsoft :: Windows
Classifier: Operating System :: MacOS
Classifier: Typing :: Typed
Requires-Dist: typing-extensions>=4.14.1
License-File: LICENSE
Summary: Core functionality for Pydantic validation and serialization
Home-Page: https://github.com/pydantic/pydantic-core
Author-email: Samuel Colvin <s@muelcolvin.com>, Adrian Garcia Badaracco <1755071+adriangb@users.noreply.github.com>, David Montague <david@pydantic.dev>, David Hewitt <mail@davidhewitt.dev>, Sydney Runkle <sydneymarierunkle@gmail.com>, Victorien Plot <contact@vctrn.dev>
License-Expression: MIT
Requires-Python: >=3.9
Project-URL: Homepage, https://github.com/pydantic/pydantic-core
Project-URL: Funding, https://github.com/sponsors/samuelcolvin
Project-URL: Source, https://github.com/pydantic/pydantic-core
